py_rekor_monitor_ss17542_sscs/__init__.py
py_rekor_monitor_ss17542_sscs/main.py
py_rekor_monitor_ss17542_sscs/merkle_proof.py
py_rekor_monitor_ss17542_sscs/util.py
py_rekor_monitor_ss17542_sscs-0.1.0.dist-info/LICENSE
py_rekor_monitor_ss17542_sscs-0.1.0.dist-info/METADATA
py_rekor_monitor_ss17542_sscs-0.1.0.dist-info/WHEEL
py_rekor_monitor_ss17542_sscs-0.1.0.dist-info/entry_points.txt
py_rekor_monitor_ss17542_sscs-0.1.0.dist-info/RECORD
