Metadata-Version: 2.1
Name: py_rekor_monitor_ss17542_sscs
Version: 0.1.0
Summary: 
Requires-Python: >=3.13,<4.0
Classifier: Programming Language :: Python :: 3
Classifier: Programming Language :: Python :: 3.13
Requires-Dist: cryptography (>=43.0.3,<44.0.0)
Requires-Dist: requests (>=2.32.3,<3.0.0)
